{
  "project_info": {
    "project_number": "61059001272",
    "firebase_url": "https://room-chat-bdb7d-default-rtdb.asia-southeast1.firebasedatabase.app",
    "project_id": "room-chat-bdb7d",
    "storage_bucket": "room-chat-bdb7d.appspot.com"
  },
  "client": [
    {
      "client_info": {
        "mobilesdk_app_id": "1:61059001272:android:996fcb2844d746dad5bd4d",
        "android_client_info": {
          "package_name": "com.example.mychatapp"
        }
      },
      "oauth_client": [
        {
          "client_id": "61059001272-v6iktemrg3cj7v5j1pktlot6ahplk3t4.apps.googleusercontent.com",
          "client_type": 3
        }
      ],
      "api_key": [
        {
          "current_key": "AIzaSyBdiUdoJVRY9beMfNiKUmE_2RyJjKN8Frs"
        }
      ],
      "services": {
        "appinvite_service": {
          "other_platform_oauth_client": [
            {
              "client_id": "61059001272-v6iktemrg3cj7v5j1pktlot6ahplk3t4.apps.googleusercontent.com",
              "client_type": 3
            }
          ]
        }
      }
    },
    {
      "client_info": {
        "mobilesdk_app_id": "1:61059001272:android:62c4652c1c57e989d5bd4d",
        "android_client_info": {
          "package_name": "com.example.roomchatapp"
        }
      },
      "oauth_client": [
        {
          "client_id": "61059001272-v6iktemrg3cj7v5j1pktlot6ahplk3t4.apps.googleusercontent.com",
          "client_type": 3
        }
      ],
      "api_key": [
        {
          "current_key": "AIzaSyBdiUdoJVRY9beMfNiKUmE_2RyJjKN8Frs"
        }
      ],
      "services": {
        "appinvite_service": {
          "other_platform_oauth_client": [
            {
              "client_id": "61059001272-v6iktemrg3cj7v5j1pktlot6ahplk3t4.apps.googleusercontent.com",
              "client_type": 3
            }
          ]
        }
      }
    }
  ],
  "configuration_version": "1"
}